{
  "behavior": "darts",
  "bucket": "tide:snatcher_squid_bucket",
  "conditions": [
    {
      "type": "tide:dimension",
      "dimensions": [
        "minecraft:the_end"
      ]
    },
    {
      "type": "tide:fluid",
      "fluid": "void"
    }
  ],
  "display_data": {
    "entity": "tide:snatcher_squid",
    "shape": "2x1",
    "x": 0.1,
    "z": -0.05
  },
  "fish": "tide:snatcher_squid",
  "journal_profile": {
    "alt_sprite": "tide:textures/item/snatcher_squid_full.png",
    "alt_sprite_size": 32,
    "description": "journal.description.tide.snatcher_squid",
    "group": "void",
    "location": "journal.info.location.void",
    "rarity": "very_rare"
  },
  "selection_weight": 6.0,
  "size": {
    "record_high_cm": 260.0,
    "typical_high_cm": 170.0,
    "typical_low_cm": 110.0
  },
  "speed": 1.5,
  "strength": 0.8
}