{
    "QuestData": {
        "ActiveQuests": [
            {
                "ExtraData": {
                },
                "QuestCompleted": 0b,
                "Quest": 1
            },
            {
                "ExtraData": {
                },
                "QuestCompleted": 0b,
                "Quest": 3
            },
            {
                "ExtraData": {
                },
                "QuestCompleted": 0b,
                "Quest": 4
            }
        ],
        "CompletedQuests": [
            {
                "Quest": 3,
                "Date": 39303517L
            },
            {
                "Quest": 4,
                "Date": 39324078L
            }
        ]
    },
    "jacket": 0,
    "FactionData": [
        {
            "Faction": 3,
            "Points": 1000
        },
        {
            "Faction": 4,
            "Points": 1600
        },
        {
            "Faction": 9,
            "Points": 1000
        }
    ],
    "face": 0,
    "ItemGiverChained": [
    ],
    "ScriptStoreddata": {
    },
    "hair": 0,
    "ItemGiversList": [
        {
            "Long": 1755560466612L,
            "Slot": 2
        },
        {
            "Long": 1755568139360L,
            "Slot": 6
        }
    ],
    "TransportData": [
    ],
    "DialogData": [
        {
            "Dialog": 4
        },
        {
            "Dialog": 6
        },
        {
            "Dialog": 7
        }
    ],
    "PlayerCompanionId": 0,
    "body": 0,
    "isActive": 0b,
    "bodyColor": 0,
    "NpcsTimers": [
    ],
    "shoes": 0,
    "leg": 0,
    "PlayerName": "BowDagenhart",
    "isMale": 0b,
    "UUID": "b6f8cc54-b92e-411e-96a3-9b3f92808674",
    "eyesColor": 0,
    "MailData": [
    ],
    "BankData": [
    ],
    "peculiarities": [I;],
    "hairColor": 0
}
